codesnip/__init__.py
codesnip/async_client.py
codesnip/cli.py
codesnip/config.py
codesnip/github_fetcher.py
codesnip/interactive_prompts.py
codesnip/multi_language_cli.py
codesnip/openai_client.py
codesnip/quality_checker.py
codesnip/setup_wizard.py
codesnip/analysis/architecture_analyzer.py
codesnip/analysis/memory_analyzer.py
codesnip/analysis/performance_profiler.py
codesnip/enterprise/enterprise_config.py
codesnip/languages/i18n.py
codesnip/languages/language_detector.py
codesnip/languages/package_manager.py
codesnip/languages/quality_checkers.py
codesnip/languages/locales/ar.json
codesnip/languages/locales/cs.json
codesnip/languages/locales/da.json
codesnip/languages/locales/de.json
codesnip/languages/locales/el.json
codesnip/languages/locales/es.json
codesnip/languages/locales/fi.json
codesnip/languages/locales/fr.json
codesnip/languages/locales/he.json
codesnip/languages/locales/hi.json
codesnip/languages/locales/hu.json
codesnip/languages/locales/id.json
codesnip/languages/locales/it.json
codesnip/languages/locales/ja.json
codesnip/languages/locales/ko.json
codesnip/languages/locales/ms.json
codesnip/languages/locales/nl.json
codesnip/languages/locales/no.json
codesnip/languages/locales/pl.json
codesnip/languages/locales/pt.json
codesnip/languages/locales/ro.json
codesnip/languages/locales/ru.json
codesnip/languages/locales/sv.json
codesnip/languages/locales/th.json
codesnip/languages/locales/tl.json
codesnip/languages/locales/tr.json
codesnip/languages/locales/vi.json
codesnip/languages/locales/zh.json
codesnip/premerge/__init__.py
codesnip/premerge/draft_release_notes.py
codesnip/premerge/risk_predictor.py
codesnip/templates/github-workflow.yml
codesnip/workflow/__init__.py
codesnip/workflow/github_integration.py
prcodesnip-1.0.0.dist-info/licenses/LICENSE
prcodesnip-1.0.0.dist-info/METADATA
prcodesnip-1.0.0.dist-info/WHEEL
prcodesnip-1.0.0.dist-info/entry_points.txt
prcodesnip-1.0.0.dist-info/top_level.txt
prcodesnip-1.0.0.dist-info/RECORD
