Metadata-Version: 2.4
Name: prcodesnip
Version: 1.0.0
Summary: AI-powered GitHub PR analysis, risk prediction, and automated release notes generation
Author-email: CodeSnip Team <support@codesnip.com>
License: MIT
Project-URL: Homepage, https://github.com/codesnip/codesnip
Project-URL: Documentation, https://docs.codesnip.com
Project-URL: Repository, https://github.com/codesnip/codesnip
Project-URL: Issues, https://github.com/codesnip/codesnip/issues
Project-URL: Changelog, https://github.com/codesnip/codesnip/blob/main/CHANGELOG.md
Keywords: github,pr,analysis,ai,release-notes,code-quality,devops,ci-cd,automation,risk-prediction
Classifier: Development Status :: 5 - Production/Stable
Classifier: Intended Audience :: Developers
Classifier: License :: OSI Approved :: MIT License
Classifier: Operating System :: OS Independent
Classifier: Programming Language :: Python :: 3
Classifier: Programming Language :: Python :: 3.8
Classifier: Programming Language :: Python :: 3.9
Classifier: Programming Language :: Python :: 3.10
Classifier: Programming Language :: Python :: 3.11
Classifier: Programming Language :: Python :: 3.12
Classifier: Topic :: Software Development :: Quality Assurance
Classifier: Topic :: Software Development :: Version Control
Classifier: Topic :: Software Development :: Libraries :: Python Modules
Requires-Python: >=3.8
License-File: LICENSE
Requires-Dist: click>=8.0.0
Requires-Dist: requests>=2.25.0
Requires-Dist: openai>=1.0.0
Requires-Dist: aiohttp>=3.8.0
Requires-Dist: psutil>=5.8.0
Requires-Dist: pyyaml>=6.0.0
Provides-Extra: dev
Requires-Dist: pytest>=6.0; extra == "dev"
Requires-Dist: coverage>=6.0; extra == "dev"
Requires-Dist: pylint>=2.15.0; extra == "dev"
Requires-Dist: bandit>=1.7.0; extra == "dev"
Requires-Dist: black>=22.0; extra == "dev"
Requires-Dist: isort>=5.10.0; extra == "dev"
Dynamic: license-file
